fastgpx/__init__.pyi
fastgpx/geo.pyi
fastgpx/polyline.pyi
fastgpx/py.typed
fastgpx.pyd
fastgpx-0.7.0.dist-info/METADATA
fastgpx-0.7.0.dist-info/WHEEL
fastgpx-0.7.0.dist-info/licenses/LICENSE.md
fastgpx-0.7.0.dist-info/RECORD
