Metadata-Version: 2.4
Name: fastgpx
Version: 0.7.0
Summary: An experimental Python library for parsing GPX files fast.
Keywords: gpx,parser,fast
Author: Thomas Thomassen
License-Expression: MIT
Classifier: Development Status :: 3 - Alpha
Classifier: Intended Audience :: Developers
Classifier: Topic :: File Formats
Classifier: Operating System :: Microsoft :: Windows
Classifier: Operating System :: POSIX :: Linux
Classifier: Programming Language :: Python :: 3.12
Classifier: Programming Language :: Python :: 3.13
Classifier: Programming Language :: Python :: 3.14
Project-URL: Homepage, https://github.com/thomthom/fastgpx
Project-URL: Repository, https://github.com/thomthom/fastgpx.git
Project-URL: Documentation, https://thomthom.github.io/fastgpx/
Requires-Python: >=3.12
